nxu/__init__.py
nxu/builder.py
nxu/config.py
nxu/expression.py
nxu/format.py
nxu/init_project.py
nxu/strategy_config.py
nxu-0.2.1.dist-info/METADATA
nxu-0.2.1.dist-info/WHEEL
nxu-0.2.1.dist-info/entry_points.txt
nxu-0.2.1.dist-info/licenses/LICENSE
nxu-0.2.1.dist-info/RECORD
