Metadata-Version: 2.4
Name: nxu
Version: 0.2.1
Summary: 给彩虹集团做的编译器
Author-email: MJ <tywf91@gmail.com>
License: DO WHAT THE FUCK YOU WANT TO PUBLIC LICENSE
License-File: LICENSE
Requires-Python: >=3.9
Requires-Dist: black>=24.1.0
Requires-Dist: pydantic>=2.10.0
Requires-Dist: typer>=0.10.0
